README.md
setup.py
lanzou/__init__.py
lanzou/api.py
lanzou.egg-info/PKG-INFO
lanzou.egg-info/SOURCES.txt
lanzou.egg-info/dependency_links.txt
lanzou.egg-info/requires.txt
lanzou.egg-info/top_level.txt