Metadata-Version: 2.1
Name: lanzou
Version: 1.0.0
Summary: LanZouCloud API
Home-page: https://github.com/zaxtyson/LanZouCloud-API
Author: zaxtyson
Author-email: zaxtyson@foxmail.com
License: UNKNOWN
Platform: UNKNOWN
Classifier: Programming Language :: Python :: 3
Classifier: Operating System :: OS Independent
